prosphera/__init__.py
prosphera/projector.py
prosphera-1.0.5.dist-info/LICENSE
prosphera-1.0.5.dist-info/METADATA
prosphera-1.0.5.dist-info/WHEEL
prosphera-1.0.5.dist-info/top_level.txt
prosphera-1.0.5.dist-info/RECORD
