Metadata-Version: 2.1
Name: prosphera
Version: 1.0.5
Summary: Visualize Multidimensional Data on a Sphere
Author-email: Volodymyr Holomb <wldmrgml@gmail.com>
License: GNU GENERAL PUBLIC LICENSE
Project-URL: Source, https://github.com/woldemarg/proshpera
Project-URL: Author, https://www.linkedin.com/in/vholomb
Keywords: visualization,analysis,clustering
Classifier: Development Status :: 4 - Beta
Classifier: License :: OSI Approved :: GNU General Public License v3 (GPLv3)
Classifier: Programming Language :: Python
Classifier: Topic :: Scientific/Engineering :: Visualization
Requires-Python: >=3.9
License-File: LICENSE
Requires-Dist: colorcet >=3.0.1
Requires-Dist: matplotlib >=3.5.3
Requires-Dist: numpy >=1.24
Requires-Dist: pandas >=2.0.3
Requires-Dist: plotly >=5.16.1
Requires-Dist: scikit-learn >=1.3.0
Requires-Dist: seaborn >=0.12.2
